setup.py
dzv_sunnyday/__init__.py
dzv_sunnyday/dzv_sunnyday.py
dzv_sunnyday.egg-info/PKG-INFO
dzv_sunnyday.egg-info/SOURCES.txt
dzv_sunnyday.egg-info/dependency_links.txt
dzv_sunnyday.egg-info/requires.txt
dzv_sunnyday.egg-info/top_level.txt